rjgtoys_thing-0.0.1-py3.8-nspkg.pth
rjgtoys/thing/__init__.py
rjgtoys_thing-0.0.1.dist-info/LICENSE
rjgtoys_thing-0.0.1.dist-info/METADATA
rjgtoys_thing-0.0.1.dist-info/WHEEL
rjgtoys_thing-0.0.1.dist-info/namespace_packages.txt
rjgtoys_thing-0.0.1.dist-info/top_level.txt
rjgtoys_thing-0.0.1.dist-info/RECORD
