Metadata-Version: 2.1
Name: rjgtoys-thing
Version: 0.0.1
Summary: A Python dict that behaves a bit like a JavaScript object
Home-page: https://github.com/bobgautier/rjgtoys-Thing
Author: Robert J. Gautier
Author-email: bob.gautier@gmail.com
License: UNKNOWN
Platform: UNKNOWN
Classifier: Programming Language :: Python :: 3
Classifier: License :: OSI Approved :: MIT License
Classifier: Operating System :: OS Independent
Requires-Python: >=3.6
